qsmcli/__init__.py
qsmcli/__main__.py
qsmcli/config.py
qsmcli/cpld.py
qsmcli/devmgr.py
qsmcli/fan.py
qsmcli/fw.py
qsmcli/host.py
qsmcli/install.py
qsmcli/interface.py
qsmcli/ipmi.py
qsmcli/ipmiexec.py
qsmcli/ipmimsg.py
qsmcli/mac.py
qsmcli/me.py
qsmcli/nic.py
qsmcli/qsmcli.py
qsmcli/qsmshell.py
qsmcli/service.py
qsmcli/subcmd.py
qsmcli/subcmdfactory.py
qsmcli/version.py
qsmcli-0.7.2.dist-info/LICENSE
qsmcli-0.7.2.dist-info/METADATA
qsmcli-0.7.2.dist-info/WHEEL
qsmcli-0.7.2.dist-info/top_level.txt
qsmcli-0.7.2.dist-info/RECORD
