Metadata-Version: 2.1
Name: qsmcli
Version: 0.7.2
Summary: A ipmitool wrapper to enhance daily operation among servers
Home-page: https://github.com/doublechiang/qsmcli
Author: Jiang Junyu
Author-email: double.chiang@gmail.com
License: UNKNOWN
Keywords: ipmitool qsm
Platform: UNKNOWN
Classifier: Programming Language :: Python :: 3
Classifier: License :: OSI Approved :: MIT License
Classifier: Operating System :: OS Independent
Requires-Dist: cmd2
Requires-Dist: elevate
